{
  "$schema": "https://turbo.build/schema.json",
  "globalDependencies": ["**/.env.*local"],
  "tasks": {
    "build": {
      "dependsOn": ["^build"],
      "env": [],
      "outputs": ["dist/**", ".next/**", "!.next/cache/**", "build/**"]
    },
    "web#build": {
      "dependsOn": ["^build"],
      "env": [
        "NODE_ENV",
        "NEXT_PUBLIC_GA_TRACKING_ID",
        "NEXT_PUBLIC_SUPABASE_URL",
        "NEXT_PUBLIC_SUPABASE_ANON_KEY"
      ],
      "outputs": [".next/**", "!.next/cache/**"]
    },
    "@maily-to/web#build": {
      "dependsOn": ["^build"],
      "env": [
        "NODE_ENV",
        "VITE_GA_TRACKING_ID",
        "VITE_SUPABASE_URL",
        "VITE_SUPABASE_ANON_KEY",
        "VITE_APP_URL"
      ],
      "outputs": ["build/**"]
    },
    "lint": {
      "dependsOn": ["^build"]
    },
    "lint:fix": {},
    "clean": {},
    "//#format": {},
    "//#format:check": {},
    "test": {},
    "test:watch": {
      "cache": false
    },
    "dev": {
      "cache": false,
      "persistent": true
    }
  }
}
